src/counters/one.vhd
-- 31-bit Up/Down Counter Custom
-- https://github.com/enthusiasticgeek/vhdl_open_cores
library ieee;
use ieee.std_logic_1164.all;
use ieee.numeric_std.all;

entity one is
port (
  clk:    in  std_logic;
  n_rst:  in  std_logic;
  cnt_stop: in std_logic;
  is_up: in std_logic;
  load_enable: in std_logic;
  load_data: in std_logic_vector(31 downto 0);
  cout:   out std_logic_vector (31 downto 0);
  overflow, underflow:   out std_logic
);
end entity;

architecture behaviour of one is
  signal cnt: signed(31 downto 0);
begin
	process (clk, n_rst, cnt_stop, is_up)
  begin
    if n_rst = '0' then
      cnt <= (others => '0');
      overflow <= '0';
      underflow <= '0';
    elsif rising_edge(clk) then
       if load_enable = '1' then
	  cnt <= signed(load_data);
       else
	  if cnt_stop /= '1' then
             if is_up = '1' then
                cnt <= signed(cnt) + 1;
		if cnt > (x"FFFFFFFF") then
                   overflow <= '1';
		end if;
	     else
                cnt <= signed(cnt) - 1;
		if cnt < 0 then
                   underflow <= '1';
		end if;
	     end if;	     
          else   
             cnt <= cnt;
	  end if;	  
       end if;
    end if;
  end process;

  cout <= std_logic_vector(cnt);
end architecture;

src/counters/one_testbench.vhd
-- 31-bit Up/Down Counter Custom Testbench
-- https://github.com/enthusiasticgeek/vhdl_open_cores
library ieee;
use ieee.std_logic_1164.all;
use ieee.numeric_std.all;

entity one_testbench is
end entity;

architecture testbench of one_testbench is
  component one
    port(
      clk:    in  std_logic;
      n_rst:  in  std_logic;
      cnt_stop: in std_logic;
      is_up: in std_logic;
      load_enable: in std_logic;
      load_data: in std_logic_vector(31 downto 0);
      cout:   out std_logic_vector (31 downto 0);
      overflow, underflow:   out std_logic
    );
  end component;

  signal  clk:    std_logic;
  signal  n_rst:  std_logic;
  signal  cnt_stop:  std_logic;
  signal  is_up:  std_logic;
  signal  load_enable:  std_logic;
  signal  load_data:   std_logic_vector (31 downto 0);
  signal  cout:   std_logic_vector (31 downto 0);
  signal  overflow, underflow:   std_logic;

begin
  dut: one port map (
                            clk=>clk, 
			    n_rst=>n_rst, 
			    cnt_stop=>cnt_stop, 
			    is_up=>is_up, 
			    load_enable=>load_enable, 
			    load_data=>load_data, 
			    cout=>cout,
			    overflow=>overflow,
			    underflow=>underflow
		    );

  process
  begin
    clk <= '0';
    wait for 5 ns;
    clk <= '1';
    wait for 5 ns;
  end process;

  process
  begin
    n_rst <= '0';
    cnt_stop <= '0';
    --is_up <= '0';
    is_up <= '1';
    --start counting from this value
    --load_data <= std_logic_vector'( x"0000FFFF");
    --load_data <= std_logic_vector'( x"00000003");   -- check underflow condition
    load_data <= std_logic_vector'( x"FFFFFFFA");     -- check overflow condition
    load_enable <= '0';
    wait for 10 ns;
    n_rst <= '1';
    load_enable <= '1';
    wait for 10 ns;
    load_enable <= '0';
    wait for 100 ns;
    cnt_stop <= '1';
    wait for 250 ns;
    wait;
  end process;
end;

src/counters/one.vcd
$date
  Tue Nov 30 22:09:58 2021
$end
$version
  GHDL v0
$end
$timescale
  1 fs
$end
$scope module standard $end
$upscope $end
$scope module std_logic_1164 $end
$upscope $end
$scope module numeric_std $end
$upscope $end
$scope module one_testbench $end
$var reg 1 ! clk $end
$var reg 1 " n_rst $end
$var reg 1 # cnt_stop $end
$var reg 1 $ is_up $end
$var reg 1 % load_enable $end
$var reg 32 & load_data[31:0] $end
$var reg 32 ' cout[31:0] $end
$var reg 1 ( overflow $end
$var reg 1 ) underflow $end
$scope module dut $end
$var reg 1 * clk $end
$var reg 1 + n_rst $end
$var reg 1 , cnt_stop $end
$var reg 1 - is_up $end
$var reg 1 . load_enable $end
$var reg 32 / load_data[31:0] $end
$var reg 32 0 cout[31:0] $end
$var reg 1 1 overflow $end
$var reg 1 2 underflow $end
$var reg 32 3 cnt[31:0] $end
$upscope $end
$upscope $end
$enddefinitions $end
#0
0!
0"
0#
1$
0%
b11111111111111111111111111111010 &
b00000000000000000000000000000000 '
0(
0)
0*
0+
0,
1-
0.
b11111111111111111111111111111010 /
b00000000000000000000000000000000 0
01
02
b00000000000000000000000000000000 3
#5000000
1!
1*
#10000000
0!
1"
1%
0*
1+
1.
#15000000
1!
b11111111111111111111111111111010 '
1*
b11111111111111111111111111111010 0
b11111111111111111111111111111010 3
#20000000
0!
0%
0*
0.
#25000000
1!
b11111111111111111111111111111011 '
1*
b11111111111111111111111111111011 0
b11111111111111111111111111111011 3
#30000000
0!
0*
#35000000
1!
b11111111111111111111111111111100 '
1*
b11111111111111111111111111111100 0
b11111111111111111111111111111100 3
#40000000
0!
0*
#45000000
1!
b11111111111111111111111111111101 '
1*
b11111111111111111111111111111101 0
b11111111111111111111111111111101 3
#50000000
0!
0*
#55000000
1!
b11111111111111111111111111111110 '
1*
b11111111111111111111111111111110 0
b11111111111111111111111111111110 3
#60000000
0!
0*
#65000000
1!
b11111111111111111111111111111111 '
1*
b11111111111111111111111111111111 0
b11111111111111111111111111111111 3
#70000000
0!
0*
#75000000
1!
b00000000000000000000000000000000 '
1*
b00000000000000000000000000000000 0
b00000000000000000000000000000000 3
#80000000
0!
0*
#85000000
1!
b00000000000000000000000000000001 '
1(
1*
b00000000000000000000000000000001 0
11
b00000000000000000000000000000001 3
#90000000
0!
0*
#95000000
1!
b00000000000000000000000000000010 '
1*
b00000000000000000000000000000010 0
b00000000000000000000000000000010 3
#100000000
0!
0*
#105000000
1!
b00000000000000000000000000000011 '
1*
b00000000000000000000000000000011 0
b00000000000000000000000000000011 3
#110000000
0!
0*
#115000000
1!
b00000000000000000000000000000100 '
1*
b00000000000000000000000000000100 0
b00000000000000000000000000000100 3
#120000000
0!
1#
0*
1,
